segmetric/__init__.py
segmetric/cli.py
segmetric/dataset.py
segmetric/evaluation.py
segmetric/metrics.py
segmetric/results.py
segmetric/utils.py
esdft_segmetric-0.1.0.dist-info/METADATA
esdft_segmetric-0.1.0.dist-info/WHEEL
esdft_segmetric-0.1.0.dist-info/entry_points.txt
esdft_segmetric-0.1.0.dist-info/top_level.txt
esdft_segmetric-0.1.0.dist-info/RECORD
