Metadata-Version: 2.1
Name: esdft-segmetric
Version: 0.1.0
Summary: A package for evaluating video object segmentation metrics.
Author: Elham Soltani Kazemi
Author-email: esdft@umsystem.edu
License: BSD 3-Clause License
Classifier: Programming Language :: Python :: 3
Classifier: License :: OSI Approved :: BSD License
Classifier: Operating System :: OS Independent
Requires-Python: >=3.8
Requires-Dist: numpy
Requires-Dist: Pillow
Requires-Dist: opencv-python
Requires-Dist: pandas
Requires-Dist: scikit-image
Requires-Dist: scikit-learn
Requires-Dist: tqdm
Requires-Dist: scipy
